QQ_Robot/__init__.cp312-win_amd64.pyd
QQ_Robot/__init__.py
QQ_Robot/config.json
QQ_Robot/db.cp312-win_amd64.pyd
QQ_Robot/db.py
QQ_Robot/handler.cp312-win_amd64.pyd
QQ_Robot/handler.py
QQ_Robot/local_logger.cp312-win_amd64.pyd
QQ_Robot/local_logger.py
QQ_Robot/main.cp312-win_amd64.pyd
QQ_Robot/main.py
QQ_Robot/message.cp312-win_amd64.pyd
QQ_Robot/message.py
QQ_Robot/processor.cp312-win_amd64.pyd
QQ_Robot/processor.py
QQ_Robot/public.cp312-win_amd64.pyd
QQ_Robot/public.py
QQ_Robot/qqApp.cp312-win_amd64.pyd
QQ_Robot/qqApp.py
qq_robot-0.1.1.dist-info/METADATA
qq_robot-0.1.1.dist-info/WHEEL
qq_robot-0.1.1.dist-info/top_level.txt
qq_robot-0.1.1.dist-info/RECORD
