Metadata-Version: 2.4
Name: QQ_Robot
Version: 0.1.1
Summary: QQ robot SDK
Author: 
Author-email: 
Requires-Python: >=3.8
